src/design/bin4_to_7seg_sec.sv
module bin4_to_7seg_sec(
    input  logic [3:0] bin,
    output logic [6:0] seg
);
    logic A, B, C, D;

    always_comb begin
        A = bin[3];
        B = bin[2];
        C = bin[1];
        D = bin[0];

        // Segmento a
        seg[0] = ~(~D | ~A & B | B & C | A & ~B & ~C);

        // Segmento b
        seg[1] = ~(~B & ~C | ~B & ~D | ~A & ~C & ~D | ~A & C & D | A & ~C & D);

        // Segmento c
        seg[2] = ~(~A & B | A & ~B | ~C & D | ~A & ~C | ~A & D);

        // Segmento d
        seg[3] = ~(~B & C & D| B & ~C & D | B & C & ~D | A & ~C & ~D | ~A & ~B & ~D);

        // Segmento e
        seg[4] = ~(A & B | A & C | A & ~D | C  & ~D | ~B & ~D);

        // Segmento f
        seg[5] = ~(A & ~B | A & C | B & ~D | ~C & ~D | ~A & B & ~C);

        // Segmento g
        seg[6] = ~(A & ~B | A & D | ~B & C | C & ~D | ~A & B & ~C);
    end
endmodule

src/sim/tb_bin4_to_7seg_anodo.sv
module tb_bin4_to_7seg_anodo;
    logic [3:0] bin;
    logic [6:0] seg;

    bin4_to_7seg_sec dut (
        .bin(bin),
        .seg(seg)
    );

    initial begin
        $display("BIN | {a,b,c,d,e,f,g}");
        $display("----+-----------------");
        for (int i = 0; i < 16; i++) begin
            bin = i;
            #1;
            $display(" %1h  | {%0b,%0b,%0b,%0b,%0b,%0b,%0b}",
                     bin, seg[0], seg[1], seg[2], seg[3], seg[4], seg[5], seg[6]);
        end
        $finish;
    end
endmodule

src/build/bin4_to_7seg.vcd
$date
	Fri Mar 28 18:49:53 2025
$end
$version
	Icarus Verilog
$end
$timescale
	1s
$end
$scope module tb_bin4_to_7seg_anodo $end
$var wire 7 ! seg [6:0] $end
$var reg 4 " bin [3:0] $end
$scope module dut $end
$var wire 4 # bin [3:0] $end
$var wire 7 $ seg [6:0] $end
$var reg 1 % A $end
$var reg 1 & B $end
$var reg 1 ' C $end
$var reg 1 ( D $end
$upscope $end
$scope begin $ivl_for_loop0 $end
$var integer 32 ) i [31:0] $end
$upscope $end
$upscope $end
$enddefinitions $end
$comment Show the parameter values. $end
$dumpall
$end
#0
$dumpvars
b0 )
x(
x'
x&
x%
bx $
b0 #
b0 "
bx !
$end
#5
b1 "
b1 #
b1 )
#10
b10 "
b10 #
b10 )
#15
b11 "
b11 #
b11 )
#20
b100 "
b100 #
b100 )
#25
b101 "
b101 #
b101 )
#30
b110 "
b110 #
b110 )
#35
b111 "
b111 #
b111 )
#40
b1000 "
b1000 #
b1000 )
#45
b1001 "
b1001 #
b1001 )
#50
b1010 "
b1010 #
b1010 )
#55
b1011 "
b1011 #
b1011 )
#60
b1100 "
b1100 #
b1100 )
#65
b1101 "
b1101 #
b1101 )
#70
b1110 "
b1110 #
b1110 )
#75
b1111 "
b1111 #
b1111 )
#80
b10000 )
